LICENSE
renoir_haml/__init__.py
renoir_haml/__version__.py
renoir_haml/elements.py
renoir_haml/ext.py
renoir_haml/hamlpy.py
renoir_haml/nodes.py
renoir_haml-1.0.0.dist-info/LICENSE
renoir_haml-1.0.0.dist-info/WHEEL
renoir_haml-1.0.0.dist-info/METADATA
renoir_haml-1.0.0.dist-info/RECORD
