Metadata-Version: 2.1
Name: renoir-haml
Version: 1.0.0
Summary: HAML syntax for Renoir templates
Home-page: https://github.com/gi0baro/renoir-haml
License: BSD-3-Clause
Keywords: web,templates,haml,renoir
Author: Giovanni Barillari
Author-email: gi0baro@d4net.org
Requires-Python: >=3.7,<4.0
Classifier: Development Status :: 5 - Production/Stable
Classifier: Environment :: Web Environment
Classifier: Intended Audience :: Developers
Classifier: License :: OSI Approved :: BSD License
Classifier: Operating System :: OS Independent
Classifier: Programming Language :: Python :: 3
Classifier: Programming Language :: Python :: 3.6
Classifier: Programming Language :: Python :: 3.7
Classifier: Programming Language :: Python :: 3.8
Classifier: Programming Language :: Python :: Implementation :: CPython
Classifier: Topic :: Internet :: WWW/HTTP :: Dynamic Content
Classifier: Topic :: Software Development :: Libraries :: Python Modules
Classifier: Topic :: Text Processing :: Markup :: HTML
Requires-Dist: renoir (>=1.1,<2.0)
Project-URL: Repository, https://github.com/gi0baro/renoir-haml
